{
    "@class": "com.kony.gen.viz.model.component.KVizLabel",
    "DNDConfig": null,
    "_height_": {
        "type": "ref",
        "value": "preferred"
    },
    "_left_": {
        "type": "string",
        "value": "55dp"
    },
    "_margin_": [
        1,
        1,
        1,
        1
    ],
    "_padding_": [
        0,
        0,
        0,
        0
    ],
    "_skin_": "s6a5e0f7b06245ccb9c4f96c6a5d7e31",
    "_text_": "DESCRIPTION",
    "_top_": {
        "type": "string",
        "value": "0px"
    },
    "_width_": {
        "type": "string",
        "value": "24%"
    },
    "_wrapping_": 2,
    "android": {
        "textStyle": {
            "letterSpacing": 0,
            "strikeThrough": false
        }
    },
    "canUpdateUI": true,
    "containerId": true,
    "containerweight": 100,
    "contentalignment": 1,
    "id": "lblRoleDescHeading",
    "info": null,
    "ipad": {
        "psp": {
            "wrapping": 2
        }
    },
    "iphone": {
        "psp": {
            "wrapping": 2
        }
    },
    "isvisible": true,
    "kuid": "f6029e4f83374dd2b3330a6ba57393e5",
    "name": "kony.ui.Label",
    "parent": "flxRolesBottomContainer",
    "pf": "segRoles",
    "texti18n": "i18n.permission.DESCRIPTION",
    "tooltip": "",
    "wType": "Label",
    "zindex": 1
}