{
    "DNDConfig": null,
    "_height_": {
        "type": "string",
        "value": "70px"
    },
    "_left_": {
        "type": "string",
        "value": "0dp"
    },
    "_margin_": [
        0,
        0,
        0,
        0
    ],
    "_orientation_": 6,
    "_padding_": [
        0,
        0,
        0,
        0
    ],
    "_percent_": true,
    "_skin_": "s8ff24328417401b877c3ceb2a5fa27c",
    "_top_": {
        "type": "string",
        "value": "55dp"
    },
    "_width_": {
        "type": "string",
        "value": "100%"
    },
    "allboxes": [],
    "autogrowmode": 0,
    "canUpdateUI": true,
    "children": [
        "subHeader",
        "flxAppFilterContainer"
    ],
    "clipbounds": true,
    "containerweight": 100,
    "enablescrolling": true,
    "id": "flxMainSubHeader",
    "info": null,
    "isvisible": true,
    "kuid": "f703111ee70f457a8c9f04d1d9705e28",
    "layouttype": 2,
    "name": "kony.ui.FlexContainer",
    "parent": "flxRightPanel",
    "pf": "frmSCAScenarios",
    "snapgridsize": 10,
    "snaptogrid": true,
    "wType": "FlexContainer",
    "widgetalignment": 1,
    "zindex": 10
}