{
    "DNDConfig": null,
    "_height_": {
        "type": "string",
        "value": "150dp"
    },
    "_left_": {
        "type": "string",
        "value": "0dp"
    },
    "_margin_": [
        0,
        0,
        0,
        0
    ],
    "_orientation_": 6,
    "_padding_": [
        0,
        0,
        0,
        0
    ],
    "_percent_": true,
    "_skin_": "s8ff24328417401b877c3ceb2a5fa27c",
    "_top_": {
        "type": "string",
        "value": "45dp"
    },
    "_width_": {
        "type": "string",
        "value": "100%"
    },
    "allboxes": [],
    "autogrowmode": 0,
    "canUpdateUI": true,
    "children": [
        "flxOtherCustomerRowByUserId",
        "lblSeperatorByUserID"
    ],
    "clipbounds": false,
    "containerweight": 100,
    "enablescrolling": true,
    "id": "flxOtherCustomerSearchDetailsByUserIdContainer",
    "info": null,
    "iscustomlayout": false,
    "isvisible": false,
    "kuid": "e8840bf06a3a481ba7fa133db7829791",
    "layouttype": 4,
    "name": "kony.ui.FlexContainer",
    "parent": "flxAddExistingUserOtherCustomer",
    "pf": "frmCompanies",
    "retaincontentalignment": false,
    "retainflexpositionproperties": false,
    "retainflowhorizontalalignment": false,
    "snapgridsize": 10,
    "snaptogrid": true,
    "vizProps": {},
    "wType": "FlexContainer",
    "widgetalignment": 1,
    "zindex": 1
}