{
    "@class": "com.kony.gen.viz.model.component.KVizButton",
    "DNDConfig": null,
    "_height_": {
        "type": "string",
        "value": "22dp"
    },
    "_margin_": [
        6,
        6,
        6,
        6
    ],
    "_padding_": [
        0,
        0,
        0,
        0
    ],
    "_right_": {
        "type": "string",
        "value": "100dp"
    },
    "_skin_": "s3c60f327c994b9595aae04de642fdbe",
    "_text_": "",
    "_top_": {
        "type": "string",
        "value": "10dp"
    },
    "_width_": {
        "type": "string",
        "value": "89px"
    },
    "canUpdateUI": true,
    "containerweight": 100,
    "contentalignment": 5,
    "desktopweb": {
        "psp": {
            "hoverSkin": "s7db9565c1ce4ed8bc9c274c79bb2eca"
        }
    },
    "displaytext": true,
    "focusskin": "s3c60f327c994b9595aae04de642fdbe",
    "id": "btnAddNote",
    "info": null,
    "isvisible": true,
    "kuid": "c25e4b4b8d7d47ffa11886aaae8c7f8a",
    "name": "kony.ui.Button",
    "parent": "flxRightDetailsCont",
    "pf": "userwidgetmodel",
    "texti18n": "i18n.userwidgetmodel.lblAddNote",
    "wType": "Button",
    "zindex": 1
}