{
    "@class": "com.kony.gen.viz.model.component.KVizLabel",
    "DNDConfig": null,
    "_height_": {
        "type": "ref",
        "value": "preferred"
    },
    "_left_": {
        "type": "string",
        "value": "10dp"
    },
    "_margin_": [
        1,
        1,
        1,
        1
    ],
    "_padding_": [
        0,
        0,
        0,
        0
    ],
    "_skin_": "s295955808f7458db5a224957b36d3c5",
    "_text_": "",
    "_top_": {
        "type": "string",
        "value": "10dp"
    },
    "_width_": {
        "type": "ref",
        "value": "preferred"
    },
    "_wrapping_": 2,
    "android": {
        "textStyle": {
            "letterSpacing": 0,
            "strikeThrough": false
        }
    },
    "canUpdateUI": true,
    "containerweight": 100,
    "contentalignment": 4,
    "id": "lblSelectLegalEntity1",
    "info": null,
    "ipad": {
        "psp": {
            "wrapping": 2
        }
    },
    "iphone": {
        "psp": {
            "wrapping": 2
        }
    },
    "iscustomlayout": false,
    "isvisible": true,
    "kuid": "e94a4e2eb9f5447dafb80eacc3065d9b",
    "name": "kony.ui.Label",
    "parent": "flxLegalEntityDropdown1",
    "pf": "frmGroups",
    "retaincontentalignment": false,
    "retainflexpositionproperties": false,
    "texti18n": "i18n.frmRoles.SelectLegalEntity",
    "tooltip": "",
    "wType": "Label"
}