{
    "@class": "com.kony.gen.viz.model.component.KVizTextBox2",
    "DNDConfig": null,
    "_height_": {
        "type": "string",
        "value": "40dp"
    },
    "_left_": {
        "type": "string",
        "value": "10dp"
    },
    "_margin_": [
        0,
        0,
        0,
        0
    ],
    "_padding_": [
        0,
        0,
        0,
        0
    ],
    "_placeholder_": "",
    "_skin_": "s89d37deb7b843f593f03c8dbf7f495a",
    "_text_": "",
    "_top_": {
        "type": "string",
        "value": "0dp"
    },
    "_width_": {
        "type": "string",
        "value": "70%"
    },
    "autocapitalize": "none",
    "autocomplete": false,
    "autocorrect": false,
    "autofilter": false,
    "canUpdateUI": true,
    "containerheight": "",
    "containerheightmode": 1,
    "containerweight": 100,
    "contentalignment": 4,
    "id": "txtSubject",
    "info": null,
    "isvisible": true,
    "keyboardtype": "A",
    "kuid": "fc6477b20b294297b4ca08c400eba856",
    "mode": "A",
    "name": "kony.ui.TextBox2",
    "parent": "flxSubjectRow",
    "pf": "userwidgetmodel",
    "securetextentry": false,
    "textinputmode": "A",
    "viewtype": "default",
    "wType": "TextField",
    "zindex": 1
}