{
    "AS_Form_c3523f9328f44c04931283206d96aeec": {
        "id": "AS_Form_c3523f9328f44c04931283206d96aeec",
        "type": "ACTION_SEQUENCE",
        "params": [{
            "datatype": "collection",
            "name": "eventobject"
        }],
        "contextObj": {
            "name": "frmRequests",
            "type": "forms",
            "platform": "",
            "KUID": "fbb8f6d21dd641128a3ef81d6a151bda"
        },
        "language": "js",
        "actions": [{
            "id": "ADD_SNIPPET_a7bab96b1f5c427a94aea649bcaedab4",
            "type": "ADD_SNIPPET",
            "codeSnippet": "this.formPreshow();",
            "parentId": null
        }]
    }
}