{
    "DNDConfig": null,
    "_height_": {
        "type": "ref",
        "value": "preferred"
    },
    "_left_": {
        "type": "string",
        "value": "0dp"
    },
    "_margin_": [
        0,
        0,
        0,
        0
    ],
    "_orientation_": 6,
    "_padding_": [
        0,
        0,
        0,
        0
    ],
    "_percent_": true,
    "_skin_": "s8ff24328417401b877c3ceb2a5fa27c",
    "_top_": {
        "type": "string",
        "value": "95dp"
    },
    "_width_": {
        "type": "string",
        "value": "100%"
    },
    "allboxes": [],
    "autogrowmode": 1,
    "canUpdateUI": true,
    "children": [
        "segPermission"
    ],
    "clipbounds": true,
    "containerweight": 100,
    "enablescrolling": true,
    "id": "flxSegPermission",
    "info": null,
    "iscustomlayout": false,
    "isvisible": true,
    "kuid": "dffe84c18f134ba9952e4d3e55062415",
    "layouttype": 2,
    "name": "kony.ui.FlexContainer",
    "parent": "flxAddPermssions",
    "pf": "frmRoles",
    "retaincontentalignment": false,
    "retainflexpositionproperties": false,
    "snapgridsize": 10,
    "snaptogrid": true,
    "vizProps": {},
    "wType": "FlexContainer",
    "widgetalignment": 1
}