{
    "@class": "com.kony.gen.viz.model.component.KVizUserWidget",
    "DNDConfig": null,
    "_children_": [],
    "_height_": {
        "type": "string",
        "value": "100%"
    },
    "_left_": {
        "type": "string",
        "value": "0dp"
    },
    "_margin_": [
        0,
        0,
        0,
        0
    ],
    "_orientation_": 1,
    "_padding_": [
        0,
        0,
        0,
        0
    ],
    "_percent_": true,
    "_skin_": "sa516ef9f7594cab9cedd65e77444baf",
    "_top_": {
        "type": "string",
        "value": "0dp"
    },
    "_width_": {
        "type": "ref",
        "value": "preferred"
    },
    "areflexpropsreferenced": false,
    "autogrowmode": 0,
    "canUpdateUI": true,
    "clipbounds": true,
    "containerweight": 0,
    "dataDiffs": {
        "AdvancedSearchDropDown": {
            "__events__": {},
            "__info__": {
                "isRoot": true,
                "kuid": "d4ebae04319f43dc89550f1dd479c7f9",
                "srcKUID": "4eba2848f6ba43348133740ef17cf5d1",
                "wType": "FlexContainer"
            },
            "top": {
                "Default": {
                    "type": "string",
                    "value": "0dp"
                }
            }
        },
        "flxDropDown": {
            "__events__": {},
            "__info__": {
                "kuid": "a2dd1fb952c64e65b7f0b6d5ee4acc9d",
                "srcKUID": "2df6dff4688a4a08bab6055c72b4a292",
                "wType": "FlexContainer"
            },
            "isVisible": true
        },
        "flxPopupBody": {
            "__events__": {},
            "__info__": {
                "kuid": "ia529ce63367457bb1de7ba393b5fab5",
                "srcKUID": "4eb89b4842d649b9bad6cc17d1f65d6b",
                "wType": "FlexContainer"
            }
        },
        "flxSearch": {
            "__events__": {},
            "__info__": {
                "kuid": "da8b25f5fea74051bf82e8d07d31f692",
                "srcKUID": "e5f55a8daffc4a279d17347a8c0b17fe",
                "wType": "FlexContainer"
            },
            "isVisible": true
        },
        "flxSearchCancel": {
            "__events__": {},
            "__info__": {
                "kuid": "ae9e9905481448d18ad08d2f4f5e41d5",
                "srcKUID": "d956bd81710c4ab68d628ac04bb339f4",
                "wType": "FlexContainer"
            }
        },
        "flxSearchContainer": {
            "__events__": {},
            "__info__": {
                "kuid": "e3cb30a345a64bde98276d63de5d649d",
                "srcKUID": "f7dad64520a24f6a95adde2d64439210",
                "wType": "FlexContainer"
            }
        },
        "fontIconClearSearch": {
            "__events__": {},
            "__info__": {
                "kuid": "d4763adcb9b045a788657d5e03bdf677",
                "srcKUID": "ccd8ee9d92fa4d208e5908c5d1c7c17f",
                "wType": "Label"
            }
        },
        "fontIconSearch": {
            "__events__": {},
            "__info__": {
                "kuid": "a5a1bf0e392243a5b303fcc773f78280",
                "srcKUID": "da534ed1b1144f4e90ed352f5730a7d1",
                "wType": "Label"
            }
        },
        "richTexNoResult": {
            "__events__": {},
            "__info__": {
                "kuid": "a36d505172a64a4e8855642f107031d3",
                "srcKUID": "hc344551470842249fffa1a53b8a99de",
                "wType": "RichText"
            }
        },
        "sgmentData": {
            "__events__": {},
            "__info__": {
                "kuid": "e2266e39387a4655949aa4ad9e36f734",
                "srcKUID": "f793c4e9bb42412ab75e799a39ef66fa",
                "wType": "Segment"
            }
        },
        "tbxSearchBox": {
            "__events__": {},
            "__info__": {
                "kuid": "j39d1a86f4ed404497bc2cbd1819fb93",
                "srcKUID": "e323e816d63e4f27b0e7a96b8bb2fe1e",
                "wType": "TextField"
            }
        }
    },
    "enablescrolling": true,
    "id": "AdvancedSearchDropDown",
    "info": null,
    "isdatareferenced": false,
    "isvisible": true,
    "kuid": "d4ebae04319f43dc89550f1dd479c7f9",
    "layouttype": 2,
    "masterType": 0,
    "name": "kony.ui.UserWidgetInstance",
    "parent": "flxRequestType",
    "pf": "frmRequests",
    "snapgridsize": 10,
    "snaptogrid": true,
    "sourceUserWidget": "4eba2848f6ba43348133740ef17cf5d1",
    "wType": "UserWidgetInstance",
    "zindex": 100
}